adventuregeneratorlib/__init__.py
adventuregeneratorlib/myfunctions.py
adventuregeneratorlib-0.1.0.dist-info/METADATA
adventuregeneratorlib-0.1.0.dist-info/WHEEL
adventuregeneratorlib-0.1.0.dist-info/top_level.txt
adventuregeneratorlib-0.1.0.dist-info/RECORD
