Metadata-Version: 2.1
Name: adventuregeneratorlib
Version: 0.1.0
Summary: Randomizes stuff
Home-page: UNKNOWN
Author: Jefl17
Author-email: UNKNOWN
License: thingy-a-magic
Platform: UNKNOWN
